quant_met/__init__.py
quant_met/utils.py
quant_met/bdg/__init__.py
quant_met/bdg/bdg_hamiltonian.py
quant_met/bdg/gap_equation.py
quant_met/bdg/sc_current.py
quant_met/bdg/superfluid_weight.py
quant_met/cli/__init__.py
quant_met/cli/crit_temp.py
quant_met/cli/main.py
quant_met/cli/q_analysis.py
quant_met/cli/q_loop.py
quant_met/cli/scf.py
quant_met/parameters/__init__.py
quant_met/parameters/control.py
quant_met/parameters/main.py
quant_met/quantum_geometry/__init__.py
quant_met/quantum_geometry/qgt.py
quant_met/routines/__init__.py
quant_met/routines/analyse_q_data.py
quant_met/routines/loop_over_q.py
quant_met/routines/search_crit_temp.py
quant_met/routines/self_consistency.py
quant_met-0.1.3.dist-info/METADATA
quant_met-0.1.3.dist-info/WHEEL
quant_met-0.1.3.dist-info/entry_points.txt
quant_met-0.1.3.dist-info/licenses/LICENSE.txt
quant_met-0.1.3.dist-info/RECORD
