Metadata-Version: 2.4
Name: quant-met
Version: 0.1.3
Summary: Calculate superconductivity in flat-band systems.
Author-email: Tjark Sievers <tjarksievers@icloud.com>
License-File: LICENSE.txt
Requires-Python: >=3.11
Requires-Dist: click>=8.1.8
Requires-Dist: h5py>=3.12.1
Requires-Dist: matplotlib>=3.10.0
Requires-Dist: numba>=0.61.0
Requires-Dist: numpy>=2.1
Requires-Dist: numpydantic>=1.6.8
Requires-Dist: pandas>=2.2.3
Requires-Dist: pydantic>=2.10.4
Requires-Dist: pyyaml>=6.0.2
Requires-Dist: scipy>=1.15.0
Requires-Dist: sisl[viz]>0.16.0
Requires-Dist: tables>=3.10.2
Requires-Dist: tbmodels>=1.4.3
